helmsman/__init__.py
helmsman/chart.py
helmsman/jmespath.py
helmsman/kind.py
helmsman-0.1.8.dist-info/entry_points.txt
helmsman-0.1.8.dist-info/LICENSE.rst
helmsman-0.1.8.dist-info/WHEEL
helmsman-0.1.8.dist-info/METADATA
helmsman-0.1.8.dist-info/RECORD
