Metadata-Version: 2.1
Name: helmsman
Version: 0.1.8
Summary: Helmsman is a test framework for helm
Home-page: https://github.com/mrlyc/helmsman
Keywords: helmsman
Author: MrLYC
Author-email: imyikong@gmail.com
Requires-Python: >=3.7,<3.11
Classifier: Development Status :: 2 - Pre-Alpha
Classifier: Intended Audience :: Developers
Classifier: License :: OSI Approved :: MIT License
Classifier: Natural Language :: English
Classifier: Programming Language :: Python :: 3
Classifier: Programming Language :: Python :: 3.10
Classifier: Programming Language :: Python :: 3.7
Classifier: Programming Language :: Python :: 3.8
Classifier: Programming Language :: Python :: 3.9
Requires-Dist: PyYAML (>=6.0,<7.0)
Requires-Dist: jmespath (>=0.10.0,<0.11.0)
Requires-Dist: py-linq (>=1.3.0,<2.0.0)
Project-URL: Bug Tracker, https://github.com/mrlyc/helmsman/issues
Project-URL: Documentation, https://helmsman.readthedocs.io
Project-URL: Repository, https://github.com/mrlyc/helmsman
